{
  "metadata": {
    "expansion_timestamp": "2025-07-09T11:58:34.365944",
    "existing_committees": 240,
    "new_committees_generated": 135,
    "total_projected_committees": 375,
    "target_goal": 815,
    "target_coverage": "46.0%",
    "expansion_strategy": "strategic_pattern_based",
    "chamber_breakdown_new": {
      "House": 69,
      "Senate": 66,
      "Joint": 0
    },
    "type_breakdown_new": {
      "Standing": 7,
      "Subcommittee": 128,
      "Joint": 0
    }
  },
  "new_committees": [
    {
      "name": "Committee on the Budget",
      "chamber": "House",
      "committee_code": "hsbu00",
      "congress_gov_id": "hsbu00",
      "committee_type": "Standing",
      "is_active": true,
      "is_subcommittee": false,
      "website": "https://www.congress.gov/committees/house/hsbu00",
      "source_url": "strategic_expansion"
    },
    {
      "name": "Committee on House Administration",
      "chamber": "House",
      "committee_code": "hsha00",
      "congress_gov_id": "hsha00",
      "committee_type": "Standing",
      "is_active": true,
      "is_subcommittee": false,
      "website": "https://www.congress.gov/committees/house/hsha00",
      "source_url": "strategic_expansion"
    },
    {
      "name": "Committee on Rules",
      "chamber": "House",
      "committee_code": "hsru00",
      "congress_gov_id": "hsru00",
      "committee_type": "Standing",
      "is_active": true,
      "is_subcommittee": false,
      "website": "https://www.congress.gov/committees/house/hsru00",
      "source_url": "strategic_expansion"
    },
    {
      "name": "Committee on Standards of Official Conduct",
      "chamber": "House",
      "committee_code": "hsso00",
      "congress_gov_id": "hsso00",
      "committee_type": "Standing",
      "is_active": true,
      "is_subcommittee": false,
      "website": "https://www.congress.gov/committees/house/hsso00",
      "source_url": "strategic_expansion"
    },
    {
      "name": "Committee on the Budget",
      "chamber": "Senate",
      "committee_code": "ssbu00",
      "congress_gov_id": "ssbu00",
      "committee_type": "Standing",
      "is_active": true,
      "is_subcommittee": false,
      "website": "https://www.congress.gov/committees/senate/ssbu00",
      "source_url": "strategic_expansion"
    },
    {
      "name": "Committee on Agriculture, Nutrition, and Forestry",
      "chamber": "Senate",
      "committee_code": "ssag00",
      "congress_gov_id": "ssag00",
      "committee_type": "Standing",
      "is_active": true,
      "is_subcommittee": false,
      "website": "https://www.congress.gov/committees/senate/ssag00",
      "source_url": "strategic_expansion"
    },
    {
      "name": "Committee on Indian Affairs",
      "chamber": "Senate",
      "committee_code": "ssin00",
      "congress_gov_id": "ssin00",
      "committee_type": "Standing",
      "is_active": true,
      "is_subcommittee": false,
      "website": "https://www.congress.gov/committees/senate/ssin00",
      "source_url": "strategic_expansion"
    },
    {
      "name": "Subcommittee on Agriculture, Rural Development, Food and Drug Administration, and Related Agencies",
      "chamber": "House",
      "committee_code": "hsap01",
      "congress_gov_id": "hsap01",
      "committee_type": "Subcommittee",
      "is_active": true,
      "is_subcommittee": true,
      "parent_committee_code": "hsap00",
      "website": "https://www.congress.gov/committees/house/hsap01",
      "source_url": "strategic_expansion_subcommittee"
    },
    {
      "name": "Subcommittee on Financial Services and General Government",
      "chamber": "House",
      "committee_code": "hsap05",
      "congress_gov_id": "hsap05",
      "committee_type": "Subcommittee",
      "is_active": true,
      "is_subcommittee": true,
      "parent_committee_code": "hsap00",
      "website": "https://www.congress.gov/committees/house/hsap05",
      "source_url": "strategic_expansion_subcommittee"
    },
    {
      "name": "Subcommittee on Homeland Security",
      "chamber": "House",
      "committee_code": "hsap06",
      "congress_gov_id": "hsap06",
      "committee_type": "Subcommittee",
      "is_active": true,
      "is_subcommittee": true,
      "parent_committee_code": "hsap00",
      "website": "https://www.congress.gov/committees/house/hsap06",
      "source_url": "strategic_expansion_subcommittee"
    },
    {
      "name": "Subcommittee on Interior, Environment, and Related Agencies",
      "chamber": "House",
      "committee_code": "hsap07",
      "congress_gov_id": "hsap07",
      "committee_type": "Subcommittee",
      "is_active": true,
      "is_subcommittee": true,
      "parent_committee_code": "hsap00",
      "website": "https://www.congress.gov/committees/house/hsap07",
      "source_url": "strategic_expansion_subcommittee"
    },
    {
      "name": "Subcommittee on Labor, Health and Human Services, Education, and Related Agencies",
      "chamber": "House",
      "committee_code": "hsap08",
      "congress_gov_id": "hsap08",
      "committee_type": "Subcommittee",
      "is_active": true,
      "is_subcommittee": true,
      "parent_committee_code": "hsap00",
      "website": "https://www.congress.gov/committees/house/hsap08",
      "source_url": "strategic_expansion_subcommittee"
    },
    {
      "name": "Subcommittee on Legislative Branch",
      "chamber": "House",
      "committee_code": "hsap09",
      "congress_gov_id": "hsap09",
      "committee_type": "Subcommittee",
      "is_active": true,
      "is_subcommittee": true,
      "parent_committee_code": "hsap00",
      "website": "https://www.congress.gov/committees/house/hsap09",
      "source_url": "strategic_expansion_subcommittee"
    },
    {
      "name": "Subcommittee on Military Construction, Veterans Affairs, and Related Agencies",
      "chamber": "House",
      "committee_code": "hsap10",
      "congress_gov_id": "hsap10",
      "committee_type": "Subcommittee",
      "is_active": true,
      "is_subcommittee": true,
      "parent_committee_code": "hsap00",
      "website": "https://www.congress.gov/committees/house/hsap10",
      "source_url": "strategic_expansion_subcommittee"
    },
    {
      "name": "Subcommittee on State, Foreign Operations, and Related Programs",
      "chamber": "House",
      "committee_code": "hsap11",
      "congress_gov_id": "hsap11",
      "committee_type": "Subcommittee",
      "is_active": true,
      "is_subcommittee": true,
      "parent_committee_code": "hsap00",
      "website": "https://www.congress.gov/committees/house/hsap11",
      "source_url": "strategic_expansion_subcommittee"
    },
    {
      "name": "Subcommittee on Transportation, Housing and Urban Development, and Related Agencies",
      "chamber": "House",
      "committee_code": "hsap12",
      "congress_gov_id": "hsap12",
      "committee_type": "Subcommittee",
      "is_active": true,
      "is_subcommittee": true,
      "parent_committee_code": "hsap00",
      "website": "https://www.congress.gov/committees/house/hsap12",
      "source_url": "strategic_expansion_subcommittee"
    },
    {
      "name": "Subcommittee on Energy and Water Development",
      "chamber": "Senate",
      "committee_code": "ssap04",
      "congress_gov_id": "ssap04",
      "committee_type": "Subcommittee",
      "is_active": true,
      "is_subcommittee": true,
      "parent_committee_code": "ssap00",
      "website": "https://www.congress.gov/committees/senate/ssap04",
      "source_url": "strategic_expansion_subcommittee"
    },
    {
      "name": "Subcommittee on Financial Services and General Government",
      "chamber": "Senate",
      "committee_code": "ssap05",
      "congress_gov_id": "ssap05",
      "committee_type": "Subcommittee",
      "is_active": true,
      "is_subcommittee": true,
      "parent_committee_code": "ssap00",
      "website": "https://www.congress.gov/committees/senate/ssap05",
      "source_url": "strategic_expansion_subcommittee"
    },
    {
      "name": "Subcommittee on Homeland Security",
      "chamber": "Senate",
      "committee_code": "ssap06",
      "congress_gov_id": "ssap06",
      "committee_type": "Subcommittee",
      "is_active": true,
      "is_subcommittee": true,
      "parent_committee_code": "ssap00",
      "website": "https://www.congress.gov/committees/senate/ssap06",
      "source_url": "strategic_expansion_subcommittee"
    },
    {
      "name": "Subcommittee on Interior, Environment, and Related Agencies",
      "chamber": "Senate",
      "committee_code": "ssap07",
      "congress_gov_id": "ssap07",
      "committee_type": "Subcommittee",
      "is_active": true,
      "is_subcommittee": true,
      "parent_committee_code": "ssap00",
      "website": "https://www.congress.gov/committees/senate/ssap07",
      "source_url": "strategic_expansion_subcommittee"
    },
    {
      "name": "Subcommittee on Labor, Health and Human Services, Education, and Related Agencies",
      "chamber": "Senate",
      "committee_code": "ssap08",
      "congress_gov_id": "ssap08",
      "committee_type": "Subcommittee",
      "is_active": true,
      "is_subcommittee": true,
      "parent_committee_code": "ssap00",
      "website": "https://www.congress.gov/committees/senate/ssap08",
      "source_url": "strategic_expansion_subcommittee"
    },
    {
      "name": "Subcommittee on Legislative Branch",
      "chamber": "Senate",
      "committee_code": "ssap09",
      "congress_gov_id": "ssap09",
      "committee_type": "Subcommittee",
      "is_active": true,
      "is_subcommittee": true,
      "parent_committee_code": "ssap00",
      "website": "https://www.congress.gov/committees/senate/ssap09",
      "source_url": "strategic_expansion_subcommittee"
    },
    {
      "name": "Subcommittee on Military Construction, Veterans Affairs, and Related Agencies",
      "chamber": "Senate",
      "committee_code": "ssap10",
      "congress_gov_id": "ssap10",
      "committee_type": "Subcommittee",
      "is_active": true,
      "is_subcommittee": true,
      "parent_committee_code": "ssap00",
      "website": "https://www.congress.gov/committees/senate/ssap10",
      "source_url": "strategic_expansion_subcommittee"
    },
    {
      "name": "Subcommittee on State, Foreign Operations, and Related Programs",
      "chamber": "Senate",
      "committee_code": "ssap11",
      "congress_gov_id": "ssap11",
      "committee_type": "Subcommittee",
      "is_active": true,
      "is_subcommittee": true,
      "parent_committee_code": "ssap00",
      "website": "https://www.congress.gov/committees/senate/ssap11",
      "source_url": "strategic_expansion_subcommittee"
    },
    {
      "name": "Subcommittee on Transportation, Housing and Urban Development, and Related Agencies",
      "chamber": "Senate",
      "committee_code": "ssap12",
      "congress_gov_id": "ssap12",
      "committee_type": "Subcommittee",
      "is_active": true,
      "is_subcommittee": true,
      "parent_committee_code": "ssap00",
      "website": "https://www.congress.gov/committees/senate/ssap12",
      "source_url": "strategic_expansion_subcommittee"
    },
    {
      "name": "Subcommittee on Health",
      "chamber": "House",
      "committee_code": "hswm01",
      "congress_gov_id": "hswm01",
      "committee_type": "Subcommittee",
      "is_active": true,
      "is_subcommittee": true,
      "parent_committee_code": "hswm00",
      "website": "https://www.congress.gov/committees/house/hswm01",
      "source_url": "strategic_expansion_subcommittee"
    },
    {
      "name": "Subcommittee on Social Security",
      "chamber": "House",
      "committee_code": "hswm02",
      "congress_gov_id": "hswm02",
      "committee_type": "Subcommittee",
      "is_active": true,
      "is_subcommittee": true,
      "parent_committee_code": "hswm00",
      "website": "https://www.congress.gov/committees/house/hswm02",
      "source_url": "strategic_expansion_subcommittee"
    },
    {
      "name": "Subcommittee on Trade",
      "chamber": "House",
      "committee_code": "hswm03",
      "congress_gov_id": "hswm03",
      "committee_type": "Subcommittee",
      "is_active": true,
      "is_subcommittee": true,
      "parent_committee_code": "hswm00",
      "website": "https://www.congress.gov/committees/house/hswm03",
      "source_url": "strategic_expansion_subcommittee"
    },
    {
      "name": "Subcommittee on Worker and Family Support",
      "chamber": "House",
      "committee_code": "hswm04",
      "congress_gov_id": "hswm04",
      "committee_type": "Subcommittee",
      "is_active": true,
      "is_subcommittee": true,
      "parent_committee_code": "hswm00",
      "website": "https://www.congress.gov/committees/house/hswm04",
      "source_url": "strategic_expansion_subcommittee"
    },
    {
      "name": "Subcommittee on Select Revenue Measures",
      "chamber": "House",
      "committee_code": "hswm05",
      "congress_gov_id": "hswm05",
      "committee_type": "Subcommittee",
      "is_active": true,
      "is_subcommittee": true,
      "parent_committee_code": "hswm00",
      "website": "https://www.congress.gov/committees/house/hswm05",
      "source_url": "strategic_expansion_subcommittee"
    },
    {
      "name": "Subcommittee on Oversight",
      "chamber": "House",
      "committee_code": "hswm06",
      "congress_gov_id": "hswm06",
      "committee_type": "Subcommittee",
      "is_active": true,
      "is_subcommittee": true,
      "parent_committee_code": "hswm00",
      "website": "https://www.congress.gov/committees/house/hswm06",
      "source_url": "strategic_expansion_subcommittee"
    },
    {
      "name": "Subcommittee on Courts, Intellectual Property, and the Internet",
      "chamber": "House",
      "committee_code": "hsju01",
      "congress_gov_id": "hsju01",
      "committee_type": "Subcommittee",
      "is_active": true,
      "is_subcommittee": true,
      "parent_committee_code": "hsju00",
      "website": "https://www.congress.gov/committees/house/hsju01",
      "source_url": "strategic_expansion_subcommittee"
    },
    {
      "name": "Subcommittee on Crime, Terrorism, and Homeland Security",
      "chamber": "House",
      "committee_code": "hsju02",
      "congress_gov_id": "hsju02",
      "committee_type": "Subcommittee",
      "is_active": true,
      "is_subcommittee": true,
      "parent_committee_code": "hsju00",
      "website": "https://www.congress.gov/committees/house/hsju02",
      "source_url": "strategic_expansion_subcommittee"
    },
    {
      "name": "Subcommittee on Immigration and Citizenship",
      "chamber": "House",
      "committee_code": "hsju03",
      "congress_gov_id": "hsju03",
      "committee_type": "Subcommittee",
      "is_active": true,
      "is_subcommittee": true,
      "parent_committee_code": "hsju00",
      "website": "https://www.congress.gov/committees/house/hsju03",
      "source_url": "strategic_expansion_subcommittee"
    },
    {
      "name": "Subcommittee on Antitrust, Commercial, and Administrative Law",
      "chamber": "House",
      "committee_code": "hsju04",
      "congress_gov_id": "hsju04",
      "committee_type": "Subcommittee",
      "is_active": true,
      "is_subcommittee": true,
      "parent_committee_code": "hsju00",
      "website": "https://www.congress.gov/committees/house/hsju04",
      "source_url": "strategic_expansion_subcommittee"
    },
    {
      "name": "Subcommittee on Constitution, Civil Rights, and Civil Liberties",
      "chamber": "House",
      "committee_code": "hsju05",
      "congress_gov_id": "hsju05",
      "committee_type": "Subcommittee",
      "is_active": true,
      "is_subcommittee": true,
      "parent_committee_code": "hsju00",
      "website": "https://www.congress.gov/committees/house/hsju05",
      "source_url": "strategic_expansion_subcommittee"
    },
    {
      "name": "Subcommittee on Federal Courts, Oversight, Agency Action, and Federal Rights",
      "chamber": "Senate",
      "committee_code": "ssju01",
      "congress_gov_id": "ssju01",
      "committee_type": "Subcommittee",
      "is_active": true,
      "is_subcommittee": true,
      "parent_committee_code": "ssju00",
      "website": "https://www.congress.gov/committees/senate/ssju01",
      "source_url": "strategic_expansion_subcommittee"
    },
    {
      "name": "Subcommittee on Competition Policy, Antitrust, and Consumer Rights",
      "chamber": "Senate",
      "committee_code": "ssju02",
      "congress_gov_id": "ssju02",
      "committee_type": "Subcommittee",
      "is_active": true,
      "is_subcommittee": true,
      "parent_committee_code": "ssju00",
      "website": "https://www.congress.gov/committees/senate/ssju02",
      "source_url": "strategic_expansion_subcommittee"
    },
    {
      "name": "Subcommittee on Criminal Justice and Counterterrorism",
      "chamber": "Senate",
      "committee_code": "ssju03",
      "congress_gov_id": "ssju03",
      "committee_type": "Subcommittee",
      "is_active": true,
      "is_subcommittee": true,
      "parent_committee_code": "ssju00",
      "website": "https://www.congress.gov/committees/senate/ssju03",
      "source_url": "strategic_expansion_subcommittee"
    },
    {
      "name": "Subcommittee on Human Rights and the Law",
      "chamber": "Senate",
      "committee_code": "ssju04",
      "congress_gov_id": "ssju04",
      "committee_type": "Subcommittee",
      "is_active": true,
      "is_subcommittee": true,
      "parent_committee_code": "ssju00",
      "website": "https://www.congress.gov/committees/senate/ssju04",
      "source_url": "strategic_expansion_subcommittee"
    },
    {
      "name": "Subcommittee on Immigration, Citizenship, and Border Safety",
      "chamber": "Senate",
      "committee_code": "ssju05",
      "congress_gov_id": "ssju05",
      "committee_type": "Subcommittee",
      "is_active": true,
      "is_subcommittee": true,
      "parent_committee_code": "ssju00",
      "website": "https://www.congress.gov/committees/senate/ssju05",
      "source_url": "strategic_expansion_subcommittee"
    },
    {
      "name": "Subcommittee on Intellectual Property",
      "chamber": "Senate",
      "committee_code": "ssju06",
      "congress_gov_id": "ssju06",
      "committee_type": "Subcommittee",
      "is_active": true,
      "is_subcommittee": true,
      "parent_committee_code": "ssju00",
      "website": "https://www.congress.gov/committees/senate/ssju06",
      "source_url": "strategic_expansion_subcommittee"
    },
    {
      "name": "Subcommittee on Privacy, Technology, and the Law",
      "chamber": "Senate",
      "committee_code": "ssju07",
      "congress_gov_id": "ssju07",
      "committee_type": "Subcommittee",
      "is_active": true,
      "is_subcommittee": true,
      "parent_committee_code": "ssju00",
      "website": "https://www.congress.gov/committees/senate/ssju07",
      "source_url": "strategic_expansion_subcommittee"
    },
    {
      "name": "Subcommittee on Energy",
      "chamber": "House",
      "committee_code": "hsif01",
      "congress_gov_id": "hsif01",
      "committee_type": "Subcommittee",
      "is_active": true,
      "is_subcommittee": true,
      "parent_committee_code": "hsif00",
      "website": "https://www.congress.gov/committees/house/hsif01",
      "source_url": "strategic_expansion_subcommittee"
    },
    {
      "name": "Subcommittee on Environment and Climate Change",
      "chamber": "House",
      "committee_code": "hsif02",
      "congress_gov_id": "hsif02",
      "committee_type": "Subcommittee",
      "is_active": true,
      "is_subcommittee": true,
      "parent_committee_code": "hsif00",
      "website": "https://www.congress.gov/committees/house/hsif02",
      "source_url": "strategic_expansion_subcommittee"
    },
    {
      "name": "Subcommittee on Health",
      "chamber": "House",
      "committee_code": "hsif03",
      "congress_gov_id": "hsif03",
      "committee_type": "Subcommittee",
      "is_active": true,
      "is_subcommittee": true,
      "parent_committee_code": "hsif00",
      "website": "https://www.congress.gov/committees/house/hsif03",
      "source_url": "strategic_expansion_subcommittee"
    },
    {
      "name": "Subcommittee on Innovation, Data, and Commerce",
      "chamber": "House",
      "committee_code": "hsif04",
      "congress_gov_id": "hsif04",
      "committee_type": "Subcommittee",
      "is_active": true,
      "is_subcommittee": true,
      "parent_committee_code": "hsif00",
      "website": "https://www.congress.gov/committees/house/hsif04",
      "source_url": "strategic_expansion_subcommittee"
    },
    {
      "name": "Subcommittee on Oversight and Investigations",
      "chamber": "House",
      "committee_code": "hsif05",
      "congress_gov_id": "hsif05",
      "committee_type": "Subcommittee",
      "is_active": true,
      "is_subcommittee": true,
      "parent_committee_code": "hsif00",
      "website": "https://www.congress.gov/committees/house/hsif05",
      "source_url": "strategic_expansion_subcommittee"
    },
    {
      "name": "Subcommittee on Communications and Technology",
      "chamber": "House",
      "committee_code": "hsif06",
      "congress_gov_id": "hsif06",
      "committee_type": "Subcommittee",
      "is_active": true,
      "is_subcommittee": true,
      "parent_committee_code": "hsif00",
      "website": "https://www.congress.gov/committees/house/hsif06",
      "source_url": "strategic_expansion_subcommittee"
    },
    {
      "name": "Subcommittee on Cyber, Information Technologies, and Innovation",
      "chamber": "House",
      "committee_code": "hsas01",
      "congress_gov_id": "hsas01",
      "committee_type": "Subcommittee",
      "is_active": true,
      "is_subcommittee": true,
      "parent_committee_code": "hsas00",
      "website": "https://www.congress.gov/committees/house/hsas01",
      "source_url": "strategic_expansion_subcommittee"
    },
    {
      "name": "Subcommittee on Intelligence and Special Operations",
      "chamber": "House",
      "committee_code": "hsas02",
      "congress_gov_id": "hsas02",
      "committee_type": "Subcommittee",
      "is_active": true,
      "is_subcommittee": true,
      "parent_committee_code": "hsas00",
      "website": "https://www.congress.gov/committees/house/hsas02",
      "source_url": "strategic_expansion_subcommittee"
    },
    {
      "name": "Subcommittee on Military Personnel",
      "chamber": "House",
      "committee_code": "hsas03",
      "congress_gov_id": "hsas03",
      "committee_type": "Subcommittee",
      "is_active": true,
      "is_subcommittee": true,
      "parent_committee_code": "hsas00",
      "website": "https://www.congress.gov/committees/house/hsas03",
      "source_url": "strategic_expansion_subcommittee"
    },
    {
      "name": "Subcommittee on Readiness",
      "chamber": "House",
      "committee_code": "hsas04",
      "congress_gov_id": "hsas04",
      "committee_type": "Subcommittee",
      "is_active": true,
      "is_subcommittee": true,
      "parent_committee_code": "hsas00",
      "website": "https://www.congress.gov/committees/house/hsas04",
      "source_url": "strategic_expansion_subcommittee"
    },
    {
      "name": "Subcommittee on Seapower and Projection Forces",
      "chamber": "House",
      "committee_code": "hsas05",
      "congress_gov_id": "hsas05",
      "committee_type": "Subcommittee",
      "is_active": true,
      "is_subcommittee": true,
      "parent_committee_code": "hsas00",
      "website": "https://www.congress.gov/committees/house/hsas05",
      "source_url": "strategic_expansion_subcommittee"
    },
    {
      "name": "Subcommittee on Strategic Forces",
      "chamber": "House",
      "committee_code": "hsas06",
      "congress_gov_id": "hsas06",
      "committee_type": "Subcommittee",
      "is_active": true,
      "is_subcommittee": true,
      "parent_committee_code": "hsas00",
      "website": "https://www.congress.gov/committees/house/hsas06",
      "source_url": "strategic_expansion_subcommittee"
    },
    {
      "name": "Subcommittee on Tactical Air and Land Forces",
      "chamber": "House",
      "committee_code": "hsas07",
      "congress_gov_id": "hsas07",
      "committee_type": "Subcommittee",
      "is_active": true,
      "is_subcommittee": true,
      "parent_committee_code": "hsas00",
      "website": "https://www.congress.gov/committees/house/hsas07",
      "source_url": "strategic_expansion_subcommittee"
    },
    {
      "name": "Subcommittee on Airland",
      "chamber": "Senate",
      "committee_code": "ssas01",
      "congress_gov_id": "ssas01",
      "committee_type": "Subcommittee",
      "is_active": true,
      "is_subcommittee": true,
      "parent_committee_code": "ssas00",
      "website": "https://www.congress.gov/committees/senate/ssas01",
      "source_url": "strategic_expansion_subcommittee"
    },
    {
      "name": "Subcommittee on Cybersecurity",
      "chamber": "Senate",
      "committee_code": "ssas02",
      "congress_gov_id": "ssas02",
      "committee_type": "Subcommittee",
      "is_active": true,
      "is_subcommittee": true,
      "parent_committee_code": "ssas00",
      "website": "https://www.congress.gov/committees/senate/ssas02",
      "source_url": "strategic_expansion_subcommittee"
    },
    {
      "name": "Subcommittee on Emerging Threats and Capabilities",
      "chamber": "Senate",
      "committee_code": "ssas03",
      "congress_gov_id": "ssas03",
      "committee_type": "Subcommittee",
      "is_active": true,
      "is_subcommittee": true,
      "parent_committee_code": "ssas00",
      "website": "https://www.congress.gov/committees/senate/ssas03",
      "source_url": "strategic_expansion_subcommittee"
    },
    {
      "name": "Subcommittee on Personnel",
      "chamber": "Senate",
      "committee_code": "ssas04",
      "congress_gov_id": "ssas04",
      "committee_type": "Subcommittee",
      "is_active": true,
      "is_subcommittee": true,
      "parent_committee_code": "ssas00",
      "website": "https://www.congress.gov/committees/senate/ssas04",
      "source_url": "strategic_expansion_subcommittee"
    },
    {
      "name": "Subcommittee on Readiness and Management Support",
      "chamber": "Senate",
      "committee_code": "ssas05",
      "congress_gov_id": "ssas05",
      "committee_type": "Subcommittee",
      "is_active": true,
      "is_subcommittee": true,
      "parent_committee_code": "ssas00",
      "website": "https://www.congress.gov/committees/senate/ssas05",
      "source_url": "strategic_expansion_subcommittee"
    },
    {
      "name": "Subcommittee on Seapower",
      "chamber": "Senate",
      "committee_code": "ssas06",
      "congress_gov_id": "ssas06",
      "committee_type": "Subcommittee",
      "is_active": true,
      "is_subcommittee": true,
      "parent_committee_code": "ssas00",
      "website": "https://www.congress.gov/committees/senate/ssas06",
      "source_url": "strategic_expansion_subcommittee"
    },
    {
      "name": "Subcommittee on Strategic Forces",
      "chamber": "Senate",
      "committee_code": "ssas07",
      "congress_gov_id": "ssas07",
      "committee_type": "Subcommittee",
      "is_active": true,
      "is_subcommittee": true,
      "parent_committee_code": "ssas00",
      "website": "https://www.congress.gov/committees/senate/ssas07",
      "source_url": "strategic_expansion_subcommittee"
    },
    {
      "name": "Subcommittee on Capital Markets",
      "chamber": "House",
      "committee_code": "hsba01",
      "congress_gov_id": "hsba01",
      "committee_type": "Subcommittee",
      "is_active": true,
      "is_subcommittee": true,
      "parent_committee_code": "hsba00",
      "website": "https://www.congress.gov/committees/house/hsba01",
      "source_url": "strategic_expansion_subcommittee"
    },
    {
      "name": "Subcommittee on Digital Assets, Financial Technology and Inclusion",
      "chamber": "House",
      "committee_code": "hsba02",
      "congress_gov_id": "hsba02",
      "committee_type": "Subcommittee",
      "is_active": true,
      "is_subcommittee": true,
      "parent_committee_code": "hsba00",
      "website": "https://www.congress.gov/committees/house/hsba02",
      "source_url": "strategic_expansion_subcommittee"
    },
    {
      "name": "Subcommittee on Financial Institutions and Monetary Policy",
      "chamber": "House",
      "committee_code": "hsba03",
      "congress_gov_id": "hsba03",
      "committee_type": "Subcommittee",
      "is_active": true,
      "is_subcommittee": true,
      "parent_committee_code": "hsba00",
      "website": "https://www.congress.gov/committees/house/hsba03",
      "source_url": "strategic_expansion_subcommittee"
    },
    {
      "name": "Subcommittee on Housing and Insurance",
      "chamber": "House",
      "committee_code": "hsba04",
      "congress_gov_id": "hsba04",
      "committee_type": "Subcommittee",
      "is_active": true,
      "is_subcommittee": true,
      "parent_committee_code": "hsba00",
      "website": "https://www.congress.gov/committees/house/hsba04",
      "source_url": "strategic_expansion_subcommittee"
    },
    {
      "name": "Subcommittee on National Security, Illicit Finance, and International Financial Institutions",
      "chamber": "House",
      "committee_code": "hsba05",
      "congress_gov_id": "hsba05",
      "committee_type": "Subcommittee",
      "is_active": true,
      "is_subcommittee": true,
      "parent_committee_code": "hsba00",
      "website": "https://www.congress.gov/committees/house/hsba05",
      "source_url": "strategic_expansion_subcommittee"
    },
    {
      "name": "Subcommittee on Oversight and Investigations",
      "chamber": "House",
      "committee_code": "hsba06",
      "congress_gov_id": "hsba06",
      "committee_type": "Subcommittee",
      "is_active": true,
      "is_subcommittee": true,
      "parent_committee_code": "hsba00",
      "website": "https://www.congress.gov/committees/house/hsba06",
      "source_url": "strategic_expansion_subcommittee"
    },
    {
      "name": "Subcommittee on Aviation Safety, Operations, and Innovation",
      "chamber": "Senate",
      "committee_code": "sscm01",
      "congress_gov_id": "sscm01",
      "committee_type": "Subcommittee",
      "is_active": true,
      "is_subcommittee": true,
      "parent_committee_code": "sscm00",
      "website": "https://www.congress.gov/committees/senate/sscm01",
      "source_url": "strategic_expansion_subcommittee"
    },
    {
      "name": "Subcommittee on Communications, Media, and Broadband",
      "chamber": "Senate",
      "committee_code": "sscm02",
      "congress_gov_id": "sscm02",
      "committee_type": "Subcommittee",
      "is_active": true,
      "is_subcommittee": true,
      "parent_committee_code": "sscm00",
      "website": "https://www.congress.gov/committees/senate/sscm02",
      "source_url": "strategic_expansion_subcommittee"
    },
    {
      "name": "Subcommittee on Consumer Protection, Product Safety, and Data Security",
      "chamber": "Senate",
      "committee_code": "sscm03",
      "congress_gov_id": "sscm03",
      "committee_type": "Subcommittee",
      "is_active": true,
      "is_subcommittee": true,
      "parent_committee_code": "sscm00",
      "website": "https://www.congress.gov/committees/senate/sscm03",
      "source_url": "strategic_expansion_subcommittee"
    },
    {
      "name": "Subcommittee on Oceans, Fisheries, Climate Change, and Manufacturing",
      "chamber": "Senate",
      "committee_code": "sscm04",
      "congress_gov_id": "sscm04",
      "committee_type": "Subcommittee",
      "is_active": true,
      "is_subcommittee": true,
      "parent_committee_code": "sscm00",
      "website": "https://www.congress.gov/committees/senate/sscm04",
      "source_url": "strategic_expansion_subcommittee"
    },
    {
      "name": "Subcommittee on Space, Science, and Competitiveness",
      "chamber": "Senate",
      "committee_code": "sscm05",
      "congress_gov_id": "sscm05",
      "committee_type": "Subcommittee",
      "is_active": true,
      "is_subcommittee": true,
      "parent_committee_code": "sscm00",
      "website": "https://www.congress.gov/committees/senate/sscm05",
      "source_url": "strategic_expansion_subcommittee"
    },
    {
      "name": "Subcommittee on Surface Transportation, Maritime, Freight, and Ports",
      "chamber": "Senate",
      "committee_code": "sscm06",
      "congress_gov_id": "sscm06",
      "committee_type": "Subcommittee",
      "is_active": true,
      "is_subcommittee": true,
      "parent_committee_code": "sscm00",
      "website": "https://www.congress.gov/committees/senate/sscm06",
      "source_url": "strategic_expansion_subcommittee"
    },
    {
      "name": "Subcommittee on Biotechnology, Horticulture, and Research",
      "chamber": "House",
      "committee_code": "hsag01",
      "congress_gov_id": "hsag01",
      "committee_type": "Subcommittee",
      "is_active": true,
      "is_subcommittee": true,
      "parent_committee_code": "hsag00",
      "website": "https://www.congress.gov/committees/house/hsag01",
      "source_url": "strategic_expansion_additional"
    },
    {
      "name": "Subcommittee on Commodity Exchanges, Energy, and Credit",
      "chamber": "House",
      "committee_code": "hsag02",
      "congress_gov_id": "hsag02",
      "committee_type": "Subcommittee",
      "is_active": true,
      "is_subcommittee": true,
      "parent_committee_code": "hsag00",
      "website": "https://www.congress.gov/committees/house/hsag02",
      "source_url": "strategic_expansion_additional"
    },
    {
      "name": "Subcommittee on Conservation and Forestry",
      "chamber": "House",
      "committee_code": "hsag03",
      "congress_gov_id": "hsag03",
      "committee_type": "Subcommittee",
      "is_active": true,
      "is_subcommittee": true,
      "parent_committee_code": "hsag00",
      "website": "https://www.congress.gov/committees/house/hsag03",
      "source_url": "strategic_expansion_additional"
    },
    {
      "name": "Subcommittee on General Farm Commodities and Risk Management",
      "chamber": "House",
      "committee_code": "hsag04",
      "congress_gov_id": "hsag04",
      "committee_type": "Subcommittee",
      "is_active": true,
      "is_subcommittee": true,
      "parent_committee_code": "hsag00",
      "website": "https://www.congress.gov/committees/house/hsag04",
      "source_url": "strategic_expansion_additional"
    },
    {
      "name": "Subcommittee on Livestock and Foreign Agriculture",
      "chamber": "House",
      "committee_code": "hsag05",
      "congress_gov_id": "hsag05",
      "committee_type": "Subcommittee",
      "is_active": true,
      "is_subcommittee": true,
      "parent_committee_code": "hsag00",
      "website": "https://www.congress.gov/committees/house/hsag05",
      "source_url": "strategic_expansion_additional"
    },
    {
      "name": "Subcommittee on Aviation",
      "chamber": "House",
      "committee_code": "hspw01",
      "congress_gov_id": "hspw01",
      "committee_type": "Subcommittee",
      "is_active": true,
      "is_subcommittee": true,
      "parent_committee_code": "hspw00",
      "website": "https://www.congress.gov/committees/house/hspw01",
      "source_url": "strategic_expansion_additional"
    },
    {
      "name": "Subcommittee on Coast Guard and Maritime Transportation",
      "chamber": "House",
      "committee_code": "hspw02",
      "congress_gov_id": "hspw02",
      "committee_type": "Subcommittee",
      "is_active": true,
      "is_subcommittee": true,
      "parent_committee_code": "hspw00",
      "website": "https://www.congress.gov/committees/house/hspw02",
      "source_url": "strategic_expansion_additional"
    },
    {
      "name": "Subcommittee on Economic Development, Public Buildings, and Emergency Management",
      "chamber": "House",
      "committee_code": "hspw03",
      "congress_gov_id": "hspw03",
      "committee_type": "Subcommittee",
      "is_active": true,
      "is_subcommittee": true,
      "parent_committee_code": "hspw00",
      "website": "https://www.congress.gov/committees/house/hspw03",
      "source_url": "strategic_expansion_additional"
    },
    {
      "name": "Subcommittee on Highways and Transit",
      "chamber": "House",
      "committee_code": "hspw04",
      "congress_gov_id": "hspw04",
      "committee_type": "Subcommittee",
      "is_active": true,
      "is_subcommittee": true,
      "parent_committee_code": "hspw00",
      "website": "https://www.congress.gov/committees/house/hspw04",
      "source_url": "strategic_expansion_additional"
    },
    {
      "name": "Subcommittee on Railroads, Pipelines, and Hazardous Materials",
      "chamber": "House",
      "committee_code": "hspw05",
      "congress_gov_id": "hspw05",
      "committee_type": "Subcommittee",
      "is_active": true,
      "is_subcommittee": true,
      "parent_committee_code": "hspw00",
      "website": "https://www.congress.gov/committees/house/hspw05",
      "source_url": "strategic_expansion_additional"
    },
    {
      "name": "Subcommittee on Water Resources and Environment",
      "chamber": "House",
      "committee_code": "hspw06",
      "congress_gov_id": "hspw06",
      "committee_type": "Subcommittee",
      "is_active": true,
      "is_subcommittee": true,
      "parent_committee_code": "hspw00",
      "website": "https://www.congress.gov/committees/house/hspw06",
      "source_url": "strategic_expansion_additional"
    },
    {
      "name": "Subcommittee on Energy and Mineral Resources",
      "chamber": "House",
      "committee_code": "hsii01",
      "congress_gov_id": "hsii01",
      "committee_type": "Subcommittee",
      "is_active": true,
      "is_subcommittee": true,
      "parent_committee_code": "hsii00",
      "website": "https://www.congress.gov/committees/house/hsii01",
      "source_url": "strategic_expansion_additional"
    },
    {
      "name": "Subcommittee on Federal Lands",
      "chamber": "House",
      "committee_code": "hsii02",
      "congress_gov_id": "hsii02",
      "committee_type": "Subcommittee",
      "is_active": true,
      "is_subcommittee": true,
      "parent_committee_code": "hsii00",
      "website": "https://www.congress.gov/committees/house/hsii02",
      "source_url": "strategic_expansion_additional"
    },
    {
      "name": "Subcommittee on Indigenous Peoples of the United States",
      "chamber": "House",
      "committee_code": "hsii03",
      "congress_gov_id": "hsii03",
      "committee_type": "Subcommittee",
      "is_active": true,
      "is_subcommittee": true,
      "parent_committee_code": "hsii00",
      "website": "https://www.congress.gov/committees/house/hsii03",
      "source_url": "strategic_expansion_additional"
    },
    {
      "name": "Subcommittee on Oversight and Investigations",
      "chamber": "House",
      "committee_code": "hsii04",
      "congress_gov_id": "hsii04",
      "committee_type": "Subcommittee",
      "is_active": true,
      "is_subcommittee": true,
      "parent_committee_code": "hsii00",
      "website": "https://www.congress.gov/committees/house/hsii04",
      "source_url": "strategic_expansion_additional"
    },
    {
      "name": "Subcommittee on Water, Wildlife and Fisheries",
      "chamber": "House",
      "committee_code": "hsii05",
      "congress_gov_id": "hsii05",
      "committee_type": "Subcommittee",
      "is_active": true,
      "is_subcommittee": true,
      "parent_committee_code": "hsii00",
      "website": "https://www.congress.gov/committees/house/hsii05",
      "source_url": "strategic_expansion_additional"
    },
    {
      "name": "Subcommittee on Energy",
      "chamber": "House",
      "committee_code": "hssy01",
      "congress_gov_id": "hssy01",
      "committee_type": "Subcommittee",
      "is_active": true,
      "is_subcommittee": true,
      "parent_committee_code": "hssy00",
      "website": "https://www.congress.gov/committees/house/hssy01",
      "source_url": "strategic_expansion_additional"
    },
    {
      "name": "Subcommittee on Environment",
      "chamber": "House",
      "committee_code": "hssy02",
      "congress_gov_id": "hssy02",
      "committee_type": "Subcommittee",
      "is_active": true,
      "is_subcommittee": true,
      "parent_committee_code": "hssy00",
      "website": "https://www.congress.gov/committees/house/hssy02",
      "source_url": "strategic_expansion_additional"
    },
    {
      "name": "Subcommittee on Investigations and Oversight",
      "chamber": "House",
      "committee_code": "hssy03",
      "congress_gov_id": "hssy03",
      "committee_type": "Subcommittee",
      "is_active": true,
      "is_subcommittee": true,
      "parent_committee_code": "hssy00",
      "website": "https://www.congress.gov/committees/house/hssy03",
      "source_url": "strategic_expansion_additional"
    },
    {
      "name": "Subcommittee on Research and Technology",
      "chamber": "House",
      "committee_code": "hssy04",
      "congress_gov_id": "hssy04",
      "committee_type": "Subcommittee",
      "is_active": true,
      "is_subcommittee": true,
      "parent_committee_code": "hssy00",
      "website": "https://www.congress.gov/committees/house/hssy04",
      "source_url": "strategic_expansion_additional"
    },
    {
      "name": "Subcommittee on Space and Aeronautics",
      "chamber": "House",
      "committee_code": "hssy05",
      "congress_gov_id": "hssy05",
      "committee_type": "Subcommittee",
      "is_active": true,
      "is_subcommittee": true,
      "parent_committee_code": "hssy00",
      "website": "https://www.congress.gov/committees/house/hssy05",
      "source_url": "strategic_expansion_additional"
    },
    {
      "name": "Subcommittee on Border Security and Enforcement",
      "chamber": "House",
      "committee_code": "hshm01",
      "congress_gov_id": "hshm01",
      "committee_type": "Subcommittee",
      "is_active": true,
      "is_subcommittee": true,
      "parent_committee_code": "hshm00",
      "website": "https://www.congress.gov/committees/house/hshm01",
      "source_url": "strategic_expansion_additional"
    },
    {
      "name": "Subcommittee on Counterterrorism, Law Enforcement, and Intelligence",
      "chamber": "House",
      "committee_code": "hshm02",
      "congress_gov_id": "hshm02",
      "committee_type": "Subcommittee",
      "is_active": true,
      "is_subcommittee": true,
      "parent_committee_code": "hshm00",
      "website": "https://www.congress.gov/committees/house/hshm02",
      "source_url": "strategic_expansion_additional"
    },
    {
      "name": "Subcommittee on Cybersecurity and Infrastructure Protection",
      "chamber": "House",
      "committee_code": "hshm03",
      "congress_gov_id": "hshm03",
      "committee_type": "Subcommittee",
      "is_active": true,
      "is_subcommittee": true,
      "parent_committee_code": "hshm00",
      "website": "https://www.congress.gov/committees/house/hshm03",
      "source_url": "strategic_expansion_additional"
    },
    {
      "name": "Subcommittee on Emergency Management and Technology",
      "chamber": "House",
      "committee_code": "hshm04",
      "congress_gov_id": "hshm04",
      "committee_type": "Subcommittee",
      "is_active": true,
      "is_subcommittee": true,
      "parent_committee_code": "hshm00",
      "website": "https://www.congress.gov/committees/house/hshm04",
      "source_url": "strategic_expansion_additional"
    },
    {
      "name": "Subcommittee on Transportation and Maritime Security",
      "chamber": "House",
      "committee_code": "hshm05",
      "congress_gov_id": "hshm05",
      "committee_type": "Subcommittee",
      "is_active": true,
      "is_subcommittee": true,
      "parent_committee_code": "hshm00",
      "website": "https://www.congress.gov/committees/house/hshm05",
      "source_url": "strategic_expansion_additional"
    },
    {
      "name": "Subcommittee on Commodities, Risk Management, and Trade",
      "chamber": "Senate",
      "committee_code": "ssag01",
      "congress_gov_id": "ssag01",
      "committee_type": "Subcommittee",
      "is_active": true,
      "is_subcommittee": true,
      "parent_committee_code": "ssag00",
      "website": "https://www.congress.gov/committees/senate/ssag01",
      "source_url": "strategic_expansion_additional"
    },
    {
      "name": "Subcommittee on Conservation, Climate, Forestry, and Natural Resources",
      "chamber": "Senate",
      "committee_code": "ssag02",
      "congress_gov_id": "ssag02",
      "committee_type": "Subcommittee",
      "is_active": true,
      "is_subcommittee": true,
      "parent_committee_code": "ssag00",
      "website": "https://www.congress.gov/committees/senate/ssag02",
      "source_url": "strategic_expansion_additional"
    },
    {
      "name": "Subcommittee on Food and Nutrition, Specialty Crops, Organics, and Research",
      "chamber": "Senate",
      "committee_code": "ssag03",
      "congress_gov_id": "ssag03",
      "committee_type": "Subcommittee",
      "is_active": true,
      "is_subcommittee": true,
      "parent_committee_code": "ssag00",
      "website": "https://www.congress.gov/committees/senate/ssag03",
      "source_url": "strategic_expansion_additional"
    },
    {
      "name": "Subcommittee on Livestock, Dairy, Poultry, Local Food Systems, and Food Safety",
      "chamber": "Senate",
      "committee_code": "ssag04",
      "congress_gov_id": "ssag04",
      "committee_type": "Subcommittee",
      "is_active": true,
      "is_subcommittee": true,
      "parent_committee_code": "ssag00",
      "website": "https://www.congress.gov/committees/senate/ssag04",
      "source_url": "strategic_expansion_additional"
    },
    {
      "name": "Subcommittee on Energy",
      "chamber": "Senate",
      "committee_code": "sseg01",
      "congress_gov_id": "sseg01",
      "committee_type": "Subcommittee",
      "is_active": true,
      "is_subcommittee": true,
      "parent_committee_code": "sseg00",
      "website": "https://www.congress.gov/committees/senate/sseg01",
      "source_url": "strategic_expansion_additional"
    },
    {
      "name": "Subcommittee on National Parks",
      "chamber": "Senate",
      "committee_code": "sseg02",
      "congress_gov_id": "sseg02",
      "committee_type": "Subcommittee",
      "is_active": true,
      "is_subcommittee": true,
      "parent_committee_code": "sseg00",
      "website": "https://www.congress.gov/committees/senate/sseg02",
      "source_url": "strategic_expansion_additional"
    },
    {
      "name": "Subcommittee on Public Lands, Forests, and Mining",
      "chamber": "Senate",
      "committee_code": "sseg03",
      "congress_gov_id": "sseg03",
      "committee_type": "Subcommittee",
      "is_active": true,
      "is_subcommittee": true,
      "parent_committee_code": "sseg00",
      "website": "https://www.congress.gov/committees/senate/sseg03",
      "source_url": "strategic_expansion_additional"
    },
    {
      "name": "Subcommittee on Water and Power",
      "chamber": "Senate",
      "committee_code": "sseg04",
      "congress_gov_id": "sseg04",
      "committee_type": "Subcommittee",
      "is_active": true,
      "is_subcommittee": true,
      "parent_committee_code": "sseg00",
      "website": "https://www.congress.gov/committees/senate/sseg04",
      "source_url": "strategic_expansion_additional"
    },
    {
      "name": "Subcommittee on Economic Policy",
      "chamber": "Senate",
      "committee_code": "ssbk01",
      "congress_gov_id": "ssbk01",
      "committee_type": "Subcommittee",
      "is_active": true,
      "is_subcommittee": true,
      "parent_committee_code": "ssbk00",
      "website": "https://www.congress.gov/committees/senate/ssbk01",
      "source_url": "strategic_expansion_additional"
    },
    {
      "name": "Subcommittee on Financial Institutions and Consumer Protection",
      "chamber": "Senate",
      "committee_code": "ssbk02",
      "congress_gov_id": "ssbk02",
      "committee_type": "Subcommittee",
      "is_active": true,
      "is_subcommittee": true,
      "parent_committee_code": "ssbk00",
      "website": "https://www.congress.gov/committees/senate/ssbk02",
      "source_url": "strategic_expansion_additional"
    },
    {
      "name": "Subcommittee on Housing, Transportation, and Community Development",
      "chamber": "Senate",
      "committee_code": "ssbk03",
      "congress_gov_id": "ssbk03",
      "committee_type": "Subcommittee",
      "is_active": true,
      "is_subcommittee": true,
      "parent_committee_code": "ssbk00",
      "website": "https://www.congress.gov/committees/senate/ssbk03",
      "source_url": "strategic_expansion_additional"
    },
    {
      "name": "Subcommittee on National Security and International Trade and Finance",
      "chamber": "Senate",
      "committee_code": "ssbk04",
      "congress_gov_id": "ssbk04",
      "committee_type": "Subcommittee",
      "is_active": true,
      "is_subcommittee": true,
      "parent_committee_code": "ssbk00",
      "website": "https://www.congress.gov/committees/senate/ssbk04",
      "source_url": "strategic_expansion_additional"
    },
    {
      "name": "Subcommittee on Chemical Safety, Waste Management, Environmental Justice, and Regulatory Oversight",
      "chamber": "Senate",
      "committee_code": "ssev01",
      "congress_gov_id": "ssev01",
      "committee_type": "Subcommittee",
      "is_active": true,
      "is_subcommittee": true,
      "parent_committee_code": "ssev00",
      "website": "https://www.congress.gov/committees/senate/ssev01",
      "source_url": "strategic_expansion_additional"
    },
    {
      "name": "Subcommittee on Clean Air, Climate, and Nuclear Safety",
      "chamber": "Senate",
      "committee_code": "ssev02",
      "congress_gov_id": "ssev02",
      "committee_type": "Subcommittee",
      "is_active": true,
      "is_subcommittee": true,
      "parent_committee_code": "ssev00",
      "website": "https://www.congress.gov/committees/senate/ssev02",
      "source_url": "strategic_expansion_additional"
    },
    {
      "name": "Subcommittee on Fisheries, Water, and Wildlife",
      "chamber": "Senate",
      "committee_code": "ssev03",
      "congress_gov_id": "ssev03",
      "committee_type": "Subcommittee",
      "is_active": true,
      "is_subcommittee": true,
      "parent_committee_code": "ssev00",
      "website": "https://www.congress.gov/committees/senate/ssev03",
      "source_url": "strategic_expansion_additional"
    },
    {
      "name": "Subcommittee on Transportation and Infrastructure",
      "chamber": "Senate",
      "committee_code": "ssev04",
      "congress_gov_id": "ssev04",
      "committee_type": "Subcommittee",
      "is_active": true,
      "is_subcommittee": true,
      "parent_committee_code": "ssev00",
      "website": "https://www.congress.gov/committees/senate/ssev04",
      "source_url": "strategic_expansion_additional"
    },
    {
      "name": "Subcommittee on Energy, Natural Resources, and Infrastructure",
      "chamber": "Senate",
      "committee_code": "ssfi01",
      "congress_gov_id": "ssfi01",
      "committee_type": "Subcommittee",
      "is_active": true,
      "is_subcommittee": true,
      "parent_committee_code": "ssfi00",
      "website": "https://www.congress.gov/committees/senate/ssfi01",
      "source_url": "strategic_expansion_additional"
    },
    {
      "name": "Subcommittee on Fiscal Responsibility and Economic Growth",
      "chamber": "Senate",
      "committee_code": "ssfi02",
      "congress_gov_id": "ssfi02",
      "committee_type": "Subcommittee",
      "is_active": true,
      "is_subcommittee": true,
      "parent_committee_code": "ssfi00",
      "website": "https://www.congress.gov/committees/senate/ssfi02",
      "source_url": "strategic_expansion_additional"
    },
    {
      "name": "Subcommittee on Health Care",
      "chamber": "Senate",
      "committee_code": "ssfi03",
      "congress_gov_id": "ssfi03",
      "committee_type": "Subcommittee",
      "is_active": true,
      "is_subcommittee": true,
      "parent_committee_code": "ssfi00",
      "website": "https://www.congress.gov/committees/senate/ssfi03",
      "source_url": "strategic_expansion_additional"
    },
    {
      "name": "Subcommittee on International Trade, Customs, and Global Competitiveness",
      "chamber": "Senate",
      "committee_code": "ssfi04",
      "congress_gov_id": "ssfi04",
      "committee_type": "Subcommittee",
      "is_active": true,
      "is_subcommittee": true,
      "parent_committee_code": "ssfi00",
      "website": "https://www.congress.gov/committees/senate/ssfi04",
      "source_url": "strategic_expansion_additional"
    },
    {
      "name": "Subcommittee on Social Security, Pensions, and Family Policy",
      "chamber": "Senate",
      "committee_code": "ssfi05",
      "congress_gov_id": "ssfi05",
      "committee_type": "Subcommittee",
      "is_active": true,
      "is_subcommittee": true,
      "parent_committee_code": "ssfi00",
      "website": "https://www.congress.gov/committees/senate/ssfi05",
      "source_url": "strategic_expansion_additional"
    },
    {
      "name": "Subcommittee on Taxation and IRS Oversight",
      "chamber": "Senate",
      "committee_code": "ssfi06",
      "congress_gov_id": "ssfi06",
      "committee_type": "Subcommittee",
      "is_active": true,
      "is_subcommittee": true,
      "parent_committee_code": "ssfi00",
      "website": "https://www.congress.gov/committees/senate/ssfi06",
      "source_url": "strategic_expansion_additional"
    },
    {
      "name": "Subcommittee on Africa and Global Health Policy",
      "chamber": "Senate",
      "committee_code": "ssfr01",
      "congress_gov_id": "ssfr01",
      "committee_type": "Subcommittee",
      "is_active": true,
      "is_subcommittee": true,
      "parent_committee_code": "ssfr00",
      "website": "https://www.congress.gov/committees/senate/ssfr01",
      "source_url": "strategic_expansion_additional"
    },
    {
      "name": "Subcommittee on East Asia, the Pacific, and International Cybersecurity Policy",
      "chamber": "Senate",
      "committee_code": "ssfr02",
      "congress_gov_id": "ssfr02",
      "committee_type": "Subcommittee",
      "is_active": true,
      "is_subcommittee": true,
      "parent_committee_code": "ssfr00",
      "website": "https://www.congress.gov/committees/senate/ssfr02",
      "source_url": "strategic_expansion_additional"
    },
    {
      "name": "Subcommittee on Europe and Regional Security Cooperation",
      "chamber": "Senate",
      "committee_code": "ssfr03",
      "congress_gov_id": "ssfr03",
      "committee_type": "Subcommittee",
      "is_active": true,
      "is_subcommittee": true,
      "parent_committee_code": "ssfr00",
      "website": "https://www.congress.gov/committees/senate/ssfr03",
      "source_url": "strategic_expansion_additional"
    },
    {
      "name": "Subcommittee on International Development and Multilateral Institutions",
      "chamber": "Senate",
      "committee_code": "ssfr04",
      "congress_gov_id": "ssfr04",
      "committee_type": "Subcommittee",
      "is_active": true,
      "is_subcommittee": true,
      "parent_committee_code": "ssfr00",
      "website": "https://www.congress.gov/committees/senate/ssfr04",
      "source_url": "strategic_expansion_additional"
    },
    {
      "name": "Subcommittee on Near East, South Asia, Central Asia, and Counterterrorism",
      "chamber": "Senate",
      "committee_code": "ssfr05",
      "congress_gov_id": "ssfr05",
      "committee_type": "Subcommittee",
      "is_active": true,
      "is_subcommittee": true,
      "parent_committee_code": "ssfr00",
      "website": "https://www.congress.gov/committees/senate/ssfr05",
      "source_url": "strategic_expansion_additional"
    },
    {
      "name": "Subcommittee on State Department and USAID Management, International Operations, and Bilateral International Development",
      "chamber": "Senate",
      "committee_code": "ssfr06",
      "congress_gov_id": "ssfr06",
      "committee_type": "Subcommittee",
      "is_active": true,
      "is_subcommittee": true,
      "parent_committee_code": "ssfr00",
      "website": "https://www.congress.gov/committees/senate/ssfr06",
      "source_url": "strategic_expansion_additional"
    },
    {
      "name": "Subcommittee on Children and Families",
      "chamber": "Senate",
      "committee_code": "sshr01",
      "congress_gov_id": "sshr01",
      "committee_type": "Subcommittee",
      "is_active": true,
      "is_subcommittee": true,
      "parent_committee_code": "sshr00",
      "website": "https://www.congress.gov/committees/senate/sshr01",
      "source_url": "strategic_expansion_additional"
    },
    {
      "name": "Subcommittee on Employment and Workplace Safety",
      "chamber": "Senate",
      "committee_code": "sshr02",
      "congress_gov_id": "sshr02",
      "committee_type": "Subcommittee",
      "is_active": true,
      "is_subcommittee": true,
      "parent_committee_code": "sshr00",
      "website": "https://www.congress.gov/committees/senate/sshr02",
      "source_url": "strategic_expansion_additional"
    },
    {
      "name": "Subcommittee on Primary Health and Retirement Security",
      "chamber": "Senate",
      "committee_code": "sshr03",
      "congress_gov_id": "sshr03",
      "committee_type": "Subcommittee",
      "is_active": true,
      "is_subcommittee": true,
      "parent_committee_code": "sshr00",
      "website": "https://www.congress.gov/committees/senate/sshr03",
      "source_url": "strategic_expansion_additional"
    },
    {
      "name": "Subcommittee on Emerging Threats and Spending Oversight",
      "chamber": "Senate",
      "committee_code": "ssga01",
      "congress_gov_id": "ssga01",
      "committee_type": "Subcommittee",
      "is_active": true,
      "is_subcommittee": true,
      "parent_committee_code": "ssga00",
      "website": "https://www.congress.gov/committees/senate/ssga01",
      "source_url": "strategic_expansion_additional"
    },
    {
      "name": "Subcommittee on Government Operations and Border Management",
      "chamber": "Senate",
      "committee_code": "ssga02",
      "congress_gov_id": "ssga02",
      "committee_type": "Subcommittee",
      "is_active": true,
      "is_subcommittee": true,
      "parent_committee_code": "ssga00",
      "website": "https://www.congress.gov/committees/senate/ssga02",
      "source_url": "strategic_expansion_additional"
    },
    {
      "name": "Subcommittee on Investigations",
      "chamber": "Senate",
      "committee_code": "ssga03",
      "congress_gov_id": "ssga03",
      "committee_type": "Subcommittee",
      "is_active": true,
      "is_subcommittee": true,
      "parent_committee_code": "ssga00",
      "website": "https://www.congress.gov/committees/senate/ssga03",
      "source_url": "strategic_expansion_additional"
    }
  ],
  "expansion_ready": false
}